Workbook

Sheet EDT
A2: Matriz Estructura de descomposición de tareas EDT
B4: DIAS | C4: HORAS POR ACTIVIDAD O ENTREGABLE | I4: DICCIONARIO EDT
A5: Fase de Planificación Inicial | C5: Jefe de Proyecto | D5: Programador Frontend | E5: Tester QA | F5: Arquitecto de Software | G5: Programador Backend | I5: ROL ACTOR | J5: NOMBRE ACTOR
A6: Acta de Constitución del Proyecto | B6: 3 | C6: 10 | D6: 0 | E6: 0 | F6: 6 | G6: 0 | I6: Jefe de Proyecto | J6: Juan Paillán
A7: EDT – Hitos de Desarrollo y Diccionario | B7: 3 | C7: 8 | D7: 0 | E7: 0 | F7: 8 | G7: 0 | I7: Programador Frontend | J7: Almendra Pavez
A8: Carta Gantt | B8: 2 | C8: 10 | D8: 0 | E8: 0 | F8: 4 | G8: 0 | I8: Tester QA | J8: Felipe Lorca
A9: Definición de Responsabilidades (RACI) | B9: 2 | C9: 6 | D9: 0 | E9: 0 | F9: 4 | G9: 0 | I9: Arquitecto de Software | J9: Sebastián Muñoz
A10: Matriz de Riesgos | B10: 3 | C10: 6 | D10: 0 | E10: 0 | F10: 8 | G10: 0 | I10: Programador Backend | J10: Michael Rubio
A11: Plan de Pruebas Inicial | B11: 2 | C11: 2 | D11: 0 | E11: 4 | F11: 4 | G11: 0
A12: Fase de Análisis y diseño | C12: Jefe de Proyecto | D12: Programador Frontend | E12: Tester QA | F12: Arquitecto de Software | G12: Programador Backend
A13: Documento de Especificación de Requerimientos (ERS) | B13: 4 | C13: 8 | D13: 2 | E13: 0 | F13: 12 | G13: 2
A14: Casos de Uso Específicos (UML) | B14: 3 | C14: 4 | D14: 0 | E14: 0 | F14: 14 | G14: 2
A15: Plan de Costos | B15: 2 | C15: 10 | D15: 0 | E15: 0 | F15: 4 | G15: 0
A16: Mockups – Interfaz Completa del Sistema | B16: 4 | C16: 4 | D16: 12 | E16: 0 | F16: 6 | G16: 0
A17: Definición de Actividades Detalladas (EDT extendida) | B17: 2 | C17: 6 | D17: 0 | E17: 0 | F17: 6 | G17: 0
A18: Plan de Riesgos | B18: 2 | C18: 4 | D18: 0 | E18: 0 | F18: 6 | G18: 0
A19: Plan de Comunicación | B19: 1 | C19: 4 | D19: 0 | E19: 0 | F19: 2 | G19: 0
A20: Plan de Adquisiciones | B20: 1 | C20: 3 | D20: 0 | E20: 0 | F20: 3 | G20: 0
A21: Modelo de Proceso de Negocio (TO-BE) | B21: 3 | C21: 4 | D21: 0 | E21: 0 | F21: 12 | G21: 0
A22: Diagrama de Arquitectura del Sistema | B22: 3 | C22: 2 | D22: 0 | E22: 0 | F22: 16 | G22: 0
A23: Plan de Calidad | B23: 2 | C23: 4 | D23: 0 | E23: 2 | F23: 6 | G23: 0
A24: Diagrama de Actividad (UML) | B24: 2 | C24: 2 | D24: 0 | E24: 0 | F24: 10 | G24: 0
... A28: Diagrama de Clases | B28: 2 | C28: 0 | D28: 4 | E28: 0 | F28: 10 | G28: 4
A29: Fase de Construcción | C29: Jefe de Proyecto | D29: Programador Frontend | E29: Tester QA | F29: Arquitecto de Software | G29: Programador Backend
A30: Implementación del Ambiente de Desarrollo | B30: 3 | C30: 2 | D30: 6 | E30: 0 | F30: 6 | G30: 6
A31: Creación de Base de Datos, Tablas y Scripts | B31: 5 | C31: 0 | D31: 0 | E31: 0 | F31: 6 | G31: 22
A32: Minuta de Control de Programación | B32: 8 | C32: 10 | D32: 0 | E32: 0 | F32: 0 | G32: 0
A33: Matriz de Seguimiento y Status del Proyecto | B33: 8 | C33: 10 | D33: 0 | E33: 0 | F33: 0 | G33: 0
A34: Verificación de Alcances | B34: 3 | C34: 6 | D34: 0 | E34: 2 | F34: 4 | G34: 0
A35: Matriz de Gestión y Control de Cambios | B35: 6 | C35: 8 | D35: 0 | E35: 0 | F35: 0 | G35: 0
A36: Fase de implementación y cierre | C36: Jefe de Proyecto | D36: Programador Frontend | E36: Tester QA | F36: Arquitecto de Software | G36: Programador Backend
A37: Plan de Pruebas Final | B37: 2 | C37: 2 | D37: 0 | E37: 6 | F37: 2 | G37: 0
A38: Ejecución de Pruebas y Corrección de Defectos | B38: 10 | C38: 4 | D38: 8 | E38: 32 | F38: 4 | G38: 16
A39: Reporte de Estatus Final del Proyecto | B39: 2 | C39: 8 | D39: 0 | E39: 0 | F39: 2 | G39: 0
A40: Plan de Implantación (Deploy) | B40: 3 | C40: 4 | D40: 2 | E40: 2 | F40: 6 | G40: 8
A41: Plan de Soporte y Mantención | B41: 1 | C41: 4 | D41: 0 | E41: 0 | F41: 2 | G41: 0
A42: Plan de Capacitación | B42: 2 | C42: 6 | D42: 2 | E42: 0 | F42: 2 | G42: 0
A43: Manual de Usuario y Manual de Administrador | B43: 3 | C43: 6 | D43: 4 | E43: 0 | F43: 4 | G43: 2
A44: Informe de Cierre del Proyecto | B44: 2 | C44: 8 | D44: 0 | E44: 0 | F44: 2 | G44: 0

Sheet Costos Fases
A2: SIGLA | B2: ROL | C2: NOMBRE | D2: VALOR HORA HH | E2: HORAS | F2: FASE PLANIFICACION | H2: COSTO POR HORA
A3: JP | B3: Jefe de Proyecto | C3: Juan Paillán | D3: 12222 | E3: =SUM(EDT!C6:C11) -> 42 | F3: =D3*E3 -> 513324 | H3: ROL | I3: NOMBRE | J3: COSTO x HORA | K3: Sueldo mes
A4: PF | B4: Programador Frontend | C4: Almendra Pavez | D4: 6667 | E4: =SUM(EDT!D6:D11) -> 0 | F4: =D4*E4 -> 0 | H4: Jefe de Proyecto | I4: Juan Paillán | J4: =K4/20/9 -> 12222.222 | K4: 2200000
A5: QA | B5: Tester QA | C5: Felipe Lorca | D5: 5000 | E5: =SUM(EDT!E6:E11) -> 4 | F5: =D5*E5 -> 20000 | H5: Programador Frontend | I5: Almendra Pavez | J5: =K5/20/9 -> 6666.6667 | K5: 1200000
A6: AS | B6: Arquitecto de Software | C6: Sebastián Muñoz | D6: 9056 | E6: =SUM(EDT!F6:F11) -> 34 | F6: =D6*E6 -> 307904 | H6: Tester QA | I6: Felipe Lorca | J6: =K6/20/9 -> 5000 | K6: 900000
A7: PB | B7: Programador Backend | C7: Michael Rubio | D7: 6667 | E7: =SUM(EDT!G6:G11) -> 0 | F7: =D7*E7 -> 0 | H7: Arquitecto de Software | I7: Sebastián Muñoz | J7: =K7/20/9 -> 9055.5556 | K7: 1630000
B8: TOTAL FASE PLANIFICACION | F8: =SUM(F3:F7) -> 841228 | H8: Programador Backend | I8: Michael Rubio | J8: =K8/20/9 -> 6666.6667 | K8: 1200000
A11: SIGLA | B11: ROL | C11: NOMBRE | D11: VALOR HORA HH | E11: HORAS | F11: FASE DISEÑO | H11: COSTO HH POR ROL
A12: JP | B12: Jefe de Proyecto | C12: Juan Paillán | D12: 12222 | E12: =SUM(EDT!C13:C28) -> 59 | F12: =D12*E12 -> 721098 | H12: Jefe de Proyecto | I12: =F3+F12+F21+F30 -> 2187738
A13: PF | B13: Programador Frontend | C13: Almendra Pavez | D13: 6667 | E13: =SUM(EDT!D13:D28) -> 18 | F13: =D13*E13 -> 120006 | H13: Programador Frontend | I13: =F4+F13+F22+F31 -> 266680
A14: QA | B14: Tester QA | C14: Felipe Lorca | D14: 5000 | E14: =SUM(EDT!E13:E28) -> 2 | F14: =D14*E14 -> 10000 | H14: Tester QA | I14: =F5+F14+F23+F32 -> 240000
A15: AS | B15: Arquitecto de Software | C15: Sebastián Muñoz | D15: 9056 | E15: =SUM(EDT!F13:F28) -> 121 | F15: =D15*E15 -> 1095776 | H15: Arquitecto de Software | I15: =F6+F15+F24+F33 -> 1765920
A16: PB | B16: Programador Backend | C16: Michael Rubio | D16: 6667 | E16: =SUM(EDT!G13:G28) -> 32 | F16: =D16*E16 -> 213344 | H16: Programador Backend | I16: =F7+F16+F25+F34 -> 573362
B17: TOTAL FASE DISEÑO | F17: =SUM(F12:F16) -> 2160224 | H17: TOTAL HH | I17: =SUM(I12:I16) -> 5033700
A20: SIGLA | B20: ROL | C20: NOMBRE | D20: VALOR HORA HH | E20: HORAS | F20: FASE DESARROLLO | H20: COSTO POR FASE
A21: JP | B21: Jefe de Proyecto | C21: Juan Paillán | D21: 12222 | E21: =SUM(EDT!C30:C35) -> 36 | F21: =D21*E21 -> 439992 | H21: Fase de Planificación Inicial | I21: =F8 -> 841228
A22: PF | B22: Programador Frontend | C22: Almendra Pavez | D22: 6667 | E22: =SUM(EDT!D30:D35) -> 6 | F22: =D22*E22 -> 40002 | H22: Fase de Análisis y Diseño | I22: =F17 -> 2160224
A23: QA | B23: Tester QA | C23: Felipe Lorca | D23: 5000 | E23: =SUM(EDT!E30:E35) -> 2 | F23: =D23*E23 -> 10000 | H23: Fase de Construcción | I23: =F26 -> 821566
A24: AS | B24: Arquitecto de Software | C24: Sebastián Muñoz | D24: 9056 | E24: =SUM(EDT!F30:F35) -> 16 | F24: =D24*E24 -> 144896 | H24: Fase de Implementación y Cierre | I24: =F35 -> 1210682
A25: PB | B25: Programador Backend | C25: Michael Rubio | D25: 6667 | E25: =SUM(EDT!G30:G35) -> 28 | F25: =D25*E25 -> 186676 | H25: TOTAL HH FASES | I25: =SUM(I21:I24) -> 5033700
B26: TOTAL FASE CONSTRUCCION | F26: =SUM(F21:F25) -> 821566
A29: SIGLA | B29: ROL | C29: NOMBRE | D29: VALOR HORA HH | E29: HORAS | F29: FASE IMPLEMENTACION Y CIERRE | H29: Margen | I29: 1.2
A30: JP | B30: Jefe de Proyecto | C30: Juan Paillán | D30: 12222 | E30: =SUM(EDT!C37:C44) -> 42 | F30: =D30*E30 -> 513324 | H30: UTILIDAD | I30: =I25*I29 -> 6040440
A31: PF | B31: Programador Frontend | C31: Almendra Pavez | D31: 6667 | E31: =SUM(EDT!D37:D44) -> 16 | F31: =D31*E31 -> 106672 | H31: PRECIO FINAL | I31: =I25+I30 -> 11074140
A32: QA | B32: Tester QA | C32: Felipe Lorca | D32: 5000 | E32: =SUM(EDT!E37:E44) -> 40 | F32: =D32*E32 -> 200000
A33: AS | B33: Arquitecto de Software | C33: Sebastián Muñoz | D33: 9056 | E33: =SUM(EDT!F37:F44) -> 24 | F33: =D33*E33 -> 217344
A34: PB | B34: Programador Backend | C34: Michael Rubio | D34: 6667 | E34: =SUM(EDT!G37:G44) -> 26 | F34: =D34*E34 -> 173342
B35: TOTAL FASE IMPLEMENTACION Y CIERRE | F35: =SUM(F30:F34) -> 1210682

Sheet Diccionario EDT
A1: Nivel | B1: Código EDT | C1: Nombre de elemento | D1: Definición | E1: Supuestos | F1: Restricciones | G1: Riesgos | H1: Consideraciones
A2: 1 | B2: 1 | C2: Fase de Planificación Inicial | D2: Conjunto de actividades para definir los lineamientos generales, alcance y gestión del proyecto. | E2: Se cuenta con tiempo y recursos para planificación inicial. | F2: Todo debe aprobarse antes de pasar a análisis y diseño. | G2: Falta de claridad inicial puede afectar fases posteriores. | H2: La fase guía el marco de trabajo completo.
A3: 2 | B3: 45658 | C3: Elaboración del Acta de Constitución | D3: Documento que formaliza el inicio del proyecto, define objetivos, alcance y responsables. | E3: Stakeholders disponibles para revisión. | F3: Debe aprobarse antes de continuar. | G3: Retraso en validación. | H3: Requiere consenso gerencial.
A4: 2 | B4: 45689 | C4: EDT – Hitos de Desarrollo y Diccionario | D4: Desglose jerárquico de entregables y su definición. | E4: Se dispone de lineamientos de dirección. | F4: Debe reflejar todo el proyecto. | G4: Omisiones en la EDT impactan en control. | H4: Actualizar constantemente.
A5: 2 | B5: 45717 | C5: Carta Gantt | D5: Cronograma detallado con actividades, tiempos y dependencias. | E5: Se conocen las duraciones estimadas. | F5: Debe estar lista al inicio. | G5: Subestimación de tiempos. | H5: Debe revisarse periódicamente.
A6: 2 | B6: 45748 | C6: Definición de Responsabilidades (RACI) | D6: Matriz que asigna roles y responsabilidades. | E6: Roles definidos y aceptados. | F6: Todos los miembros deben estar cubiertos. | G6: Confusión en responsabilidades. | H6: Mantenerla alineada con el equipo.
A7: 2 | B7: 45778 | C7: Matriz de Riesgos | D7: Identificación de riesgos con impacto y probabilidad. | E7: Acceso a información histórica. | F7: Requiere actualización constante. | G7: Riesgos no identificados. | H7: Integrar en la gestión del proyecto.
A8: 2 | B8: 45809 | C8: Plan de Pruebas Inicial | D8: Estrategia preliminar de pruebas y validaciones. | E8: Alcance inicial definido. | F8: Se limita a requerimientos iniciales. | G8: Cambios posteriores impactan. | H8: Base para pruebas finales.
A9: 1 | B9: 2 | C9: Fase de Análisis y Diseño | D9: Actividades de levantamiento de requerimientos, modelos, planes y diseño de la solución. | E9: Stakeholders disponibles para entrevistas. | F9: Depende de la aprobación de fase 1. | G9: Requerimientos mal definidos. | H9: La calidad del diseño impacta construcción.
A10: 2 | B10: 45659 | C10: Documento ERS | D10: Especificación detallada de requerimientos funcionales y no funcionales. | E10: Usuarios colaboran. | F10: Debe estar completo antes de diseño. | G10: Omisiones críticas. | H10: Revisiones periódicas.
A11: 2 | B11: 45690 | C11: Casos de Uso UML | D11: Modelado de interacciones del sistema con actores externos. | E11: Requerimientos claros. | F11: Basado en ERS. | G11: Mal modelado genera errores posteriores. | H11: Apoyar con validación de usuarios.
A12: 2 | B12: 45718 | C12: Plan de Costos | D12: Estimación de costos por fases, roles y recursos. | E12: Tarifas definidas. | F12: Sujeto al presupuesto. | G12: Costos subestimados. | H12: Revisar ante cambios de alcance.
A13: 2 | B13: 45749 | C13: Mockups Interfaz | D13: Prototipos visuales del sistema. | E13: Herramientas disponibles. | F13: Limitado a alcance definido. | G13: Expectativas irreales de usuarios. | H13: Iterar con validaciones tempranas.
... A21: 2 | B21: 45993 | C21: Diagrama de Actividad UML | D21: Flujo detallado de procesos del sistema. | E21: Requerimientos claros. | F21: Basado en ERS. | G21: Omisiones en diagramas. | H21: Revisión con analistas.
A22: 2 | B22: 2.13 | C22: Modelo Entidad-Relación | D22: Modelo conceptual de datos. | E22: Requerimientos disponibles. | F22: Debe estar normalizado. | G22: Errores en relaciones. | H22: Revisar con DBA.
A23: 2 | B23: 2.14 | C23: Modelo Relacional Normalizado | D23: Conversión del modelo E-R en tablas normalizadas. | E23: Se cuenta con modelo E-R. | F23: Cumplir 3FN mínimo. | G23: Anomalías en diseño. | H23: Validar con consultas de prueba.
A24: 2 | B24: 2.15 | C24: Diccionario de Datos | D24: Definición de atributos de datos. | E24: Modelo relacional definido. | F24: Debe ser completo. | G24: Inconsistencias de datos. | H24: Mantener actualizado.
A25: 2 | B25: 2.16 | C25: Diagrama de Clases | D25: Modelado de clases, atributos y relaciones. | E25: ERS aprobado. | F25: Basado en UML estándar. | G25: Errores en relaciones. | H25: Revisar con arquitecto.
A26: 1 | B26: 3 | C26: Fase de Construcción | D26: Desarrollo del sistema, base de datos y control del proyecto. | E26: Recursos técnicos disponibles. | F26: Depende del diseño aprobado. | G26: Retrasos en desarrollo. | H26: Dividir en iteraciones.
A27: 2 | B27: 45660 | C27: Implementación del Ambiente | D27: Configuración de servidores y entorno de desarrollo. | E27: Hardware y software disponibles. | F27: Debe estar listo antes de programación. | G27: Fallos en infraestructura. | H27: Verificar compatibilidad.
A28: 2 | B28: 45691 | C28: Creación BD, Tablas y Scripts | D28: Implementación física de la base de datos. | E28: Modelo relacional aprobado. | F28: Cumplir estándares de seguridad. | G28: Errores de diseño impactan. | H28: Revisar con DBA.
A29: 2 | B29: 45719 | C29: Minuta de Control de Programación | D29: Registro de avances y tareas. | E29: Equipo reporta estado. | F29: Debe ser periódico. | G29: Poca disciplina en reportes. | H29: Usar herramientas ágiles.
A30: 2 | B30: 45750 | C30: Matriz Seguimiento y Status | D30: Herramienta de control de progreso. | E30: Datos actualizados. | F30: Debe alinearse al cronograma. | G30: Desactualización. | H30: Mantener automatizada.
A31: 2 | B31: 45780 | C31: Verificación de Alcances | D31: Revisión de entregables desarrollados. | E31: Criterios claros. | F31: Basado en ERS. | G31: Omisión de requisitos. | H31: Validar con stakeholders.
A32: 2 | B32: 45811 | C32: Matriz de Gestión y Control de Cambios | D32: Registro formal de solicitudes de cambio. | E32: Canal definido. | F32: Debe estar centralizada. | G32: Cambios no controlados. | H32: Aprobar vía comité de cambios.
A33: 1 | B33: 4 | C33: Fase de Implementación y Cierre | D33: Actividades para desplegar, probar y cerrar el proyecto. | E33: Ambiente de producción disponible. | F33: Depende de pruebas previas. | G33: Errores en despliegue. | H33: Realizar piloto antes del cierre.
A34: 2 | B34: 45661 | C34: Plan de Pruebas Final | D34: Estrategia definitiva de validación. | E34: Casos de prueba listos. | F34: Debe cubrir todos los requisitos. | G34: Defectos tardíos. | H34: Incluir pruebas de carga.
A35: 2 | B35: 45692 | C35: Ejecución de Pruebas | D35: Validación en ambiente real. | E35: Datos de prueba disponibles. | F35: Debe cumplir plazos. | G35: Errores críticos. | H35: Documentar resultados.
A36: 2 | B36: 45720 | C36: Reporte de Estatus Final | D36: Informe del estado global del proyecto. | E36: Toda la información recopilada. | F36: Debe ser validado. | G36: Datos incompletos. | H36: Servirá de base para cierre.
A37: 2 | B37: 45751 | C37: Plan de Implantación | D37: Estrategia de despliegue en producción. | E37: Usuarios disponibles. | F37: Debe minimizar interrupciones. | G37: Fallos en producción. | H37: Desplegar por fases.
... A41: 2 | B41: 45873 | C41: Informe de Cierre | D41: Documento final que valida cumplimiento de objetivos. | E41: Información consolidada. | F41: Debe estar validado por dirección. | G41: Rechazo del cierre. | H41: Sirve como base para lecciones aprendidas.
